{"name":"verifyBody","id":"tests.SampleTestsOrderPetStore:verifyBody","testCaseName":"tests.SampleTestsOrderPetStore","userStory":{"id":"tests.SampleTestsOrderPetStore","storyName":"Sample tests order pet store","storyClassName":"tests.SampleTestsOrderPetStore","path":"tests","type":"story"},"featureTag":{"name":"Tests/Sample tests order pet store","type":"story","displayName":"Tests/Sample tests order pet store"},"title":"Verify body","tags":[{"name":"Tests/Sample tests order pet store","type":"story","displayName":"Tests/Sample tests order pet store"}],"startTime":"2020-10-16T09:39:07.660933+03:00[Europe/Kiev]","duration":786,"projectKey":"","isManualTestingUpToDate":false,"manual":false,"testSource":"JUnit","order":0,"result":"SUCCESS"}